tkfontselector/__init__.py
tkfontselector/ask_font.py
tkfontselector/tkfontselector.py
tkfontselector/translations/__init__.py
tkfontselector/translations/get_system_locale.py
tkfontselector-1.0.11.dist-info/LICENSE.txt
tkfontselector-1.0.11.dist-info/METADATA
tkfontselector-1.0.11.dist-info/WHEEL
tkfontselector-1.0.11.dist-info/RECORD
